django_admin_logs/__init__.py
django_admin_logs/admin.py
django_admin_logs/apps.py
django_admin_logs/models.py
django_admin_logs/settings.py
django_admin_logs-1.5.0.dist-info/licenses/LICENSE
django_admin_logs-1.5.0.dist-info/METADATA
django_admin_logs-1.5.0.dist-info/WHEEL
django_admin_logs-1.5.0.dist-info/top_level.txt
django_admin_logs-1.5.0.dist-info/RECORD
